d578uv_k0hax/__init__.py
d578uv_k0hax/d578uv.py
d578uv_k0hax-0.1.20210516.2.dist-info/COPYING.md
d578uv_k0hax-0.1.20210516.2.dist-info/METADATA
d578uv_k0hax-0.1.20210516.2.dist-info/WHEEL
d578uv_k0hax-0.1.20210516.2.dist-info/top_level.txt
d578uv_k0hax-0.1.20210516.2.dist-info/RECORD
