Metadata-Version: 2.1
Name: d578uv-k0hax
Version: 0.1.20210516.2
Summary: Python library to simulate a AnyTone AT-D578UV-III hand mic
Home-page: https://github.com/K0HAX/py-at-d578-microphone
Author: Michael Englehorn
Author-email: michael+pypi@englehorn.com
License: UNKNOWN
Project-URL: Bug Tracker, https://github.com/K0HAX/py-at-d578-microphone/issues
Platform: UNKNOWN
Classifier: Programming Language :: Python :: 3
Classifier: License :: OSI Approved :: GNU General Public License v3 or later (GPLv3+)
Classifier: Operating System :: OS Independent
Requires-Python: >=3.6
Requires-Dist: pyserial
